bookcache/__init__.py
bookcache/cache.py
bookcache/errors/__init__.py
bookcache/errors/base.py
bookcache/errors/notFound.py
bookcache/py.typed
bookcache/types/CachedItem.py
bookcache/utils/runner.py
bookcache-0.0.4.dist-info/LICENCE
bookcache-0.0.4.dist-info/METADATA
bookcache-0.0.4.dist-info/WHEEL
bookcache-0.0.4.dist-info/RECORD
